[
  {
    "id": "01",
    "name": "el ataque de los tomates asesinos",
    "genre": "terror?",
    "director": "???",
    "year": "19??",
    "actors": [
      {"id": "01", "name": "nicolas cage"},
      {"id": "02", "name": " leonardo di caprio"},
      {"id": "03", "name": " natalie portman"}
    ]
  },
  {
    "id": "02",
    "name": "el padrino",
    "genre": "mafiosos",
    "director": "???",
    "year": "19??",
    "actors": [
      {"id": "01", "name": "nicolas cage"},
      {"id": "02", "name": "leonardo di caprio"},
      {"id": "03", "name": "natalie portman"}
    ]
  },
  {
    "id": "03",
    "name": "el cubo",
    "genre": "triller",
    "director": "???",
    "year": "19??",
    "actors": [
      {"id": "01", "name": "nicolas cage"},
      {"id": "02", "name": "leonardo di caprio"},
      {"id": "03", "name": "natalie portman"}
    ]
  },
  {
    "id": "4",
    "name": "el padrino 2",
    "genre": "mafiosos",
    "director": "???",
    "year": "????",
    "actors": ["leonardo di caprio", "nicolas cage", "natalie portman"]
  },
  {
    "id": "5",
    "name": "el padrino 2",
    "genre": "mafiosos",
    "director": "???",
    "year": "????",
    "actors": [
      {"id": "01", "name": "[\"leonardo di caprio\""},
      {"id": "02", "name": " \"nicolas cage\""},
      {"id": "03", "name": " \"natalie portman\"]"}
    ]
  },
  {
    "id": "6",
    "name": "el padrino 2",
    "genre": "mafiosos",
    "director": "???",
    "year": "????",
    "actors": [
      {"id": "01", "name": "leonardo di caprio"},
      {"id": "02", "name": " nicolas cage"},
      {"id": "03", "name": " natalie portman"}
    ]
  },
  {
    "id": "7",
    "name": "el padrino 2",
    "genre": "mafiosos",
    "director": "???",
    "year": "????",
    "actors": [
      {"id": "01", "name": "leonardo di caprio"},
      {"id": "02", "name": " nicolas cage"},
      {"id": "03", "name": " natalie portman"}
    ]
  },
  {
    "id": "8",
    "name": "el padrino 2",
    "genre": "mafiosos",
    "director": "???",
    "year": "????",
    "actors": [
      {"id": "01", "name": "leonardo di caprio"},
      {"id": "02", "name": " nicolas cage"},
      {"id": "03", "name": " natalie portman"}
    ]
  },
  {
    "id": "9",
    "name": "el padrino 2",
    "genre": "mafiosos",
    "director": "???",
    "year": "????",
    "actors": [
      {"id": "01", "name": "leonardo di caprio"},
      {"id": "02", "name": " nicolas cage"},
      {"id": "03", "name": " natalie portman"}
    ]
  },
  {
    "id": "10",
    "name": "el padrino 2",
    "genre": "mafiosos",
    "director": "???",
    "year": "????",
    "actors": [
      {"id": "01", "name": "leonardo di caprio"},
      {"id": "02", "name": " nicolas cage"},
      {"id": "03", "name": " natalie portman"}
    ]
  },
  {
    "id": "11",
    "name": "el padrino 2",
    "genre": "mafiosos",
    "director": "???",
    "year": "????",
    "actors": [
      {"id": "01", "name": "leonardo di caprio"},
      {"id": "02", "name": " nicolas cage"},
      {"id": "03", "name": " natalie portman"}
    ]
  },
  {
    "id": "12",
    "name": "el padrino 2",
    "genre": "mafiosos",
    "director": "???",
    "year": "????",
    "actors": [
      {"id": "01", "name": "leonardo di caprio"},
      {"id": "02", "name": " nicolas cage"},
      {"id": "03", "name": " natalie portman"}
    ]
  },
  {
    "id": "13",
    "name": "el padrino 2",
    "genre": "mafiosos",
    "director": "???",
    "year": "????",
    "actors": [
      {"id": "01", "name": "leonardo di caprio"},
      {"id": "02", "name": " nicolas cage"},
      {"id": "03", "name": " natalie portman"}
    ]
  },
  {
    "id": "14",
    "name": "el padrino 2",
    "genre": "mafiosos",
    "director": "???",
    "year": "????",
    "actors": [
      {"id": "01", "name": "leonardo di caprio"},
      {"id": "02", "name": " nicolas cage"},
      {"id": "03", "name": " natalie portman"}
    ]
  },
  {
    "id": "15",
    "name": "el padrino 2",
    "genre": "mafiosos",
    "director": "???",
    "year": "????",
    "actors": [
      {"id": "01", "name": "leonardo di caprio"},
      {"id": "02", "name": " nicolas cage"},
      {"id": "03", "name": " natalie portman"}
    ]
  },
  {
    "id": "16",
    "name": "el padrino 2",
    "genre": "mafiosos",
    "director": "???",
    "year": "????",
    "actors": [
      {"id": "01", "name": "leonardo di caprio"},
      {"id": "02", "name": " nicolas cage"},
      {"id": "03", "name": " natalie portman"}
    ]
  },
  {
    "id": "17",
    "name": "el padrino 2",
    "genre": "mafiosos",
    "director": "???",
    "year": "????",
    "actors": [
      {"id": "01", "name": "leonardo di caprio"},
      {"id": "02", "name": " nicolas cage"},
      {"id": "03", "name": " natalie portman"}
    ]
  },
  {
    "id": "18",
    "name": "el padrino 2",
    "genre": "mafiosos",
    "director": "???",
    "year": "????",
    "actors": [
      {"id": "01", "name": "leonardo di caprio"},
      {"id": "02", "name": " nicolas cage"},
      {"id": "03", "name": " natalie portman"}
    ]
  },
  {
    "id": "19",
    "name": "el padrino 2",
    "genre": "mafiosos",
    "director": "???",
    "year": "????",
    "actors": [
      {"id": "01", "name": "leonardo di caprio"},
      {"id": "02", "name": " nicolas cage"},
      {"id": "03", "name": " natalie portman"}
    ]
  },
  {
    "id": "20",
    "name": "el padrino 2",
    "genre": "mafiosos",
    "director": "???",
    "year": "????",
    "actors": [
      {"id": "01", "name": "leonardo di caprio"},
      {"id": "02", "name": " nicolas cage"},
      {"id": "03", "name": " natalie portman"}
    ]
  },
  {
    "id": "21",
    "name": "el padrino 2",
    "genre": "mafiosos",
    "director": "???",
    "year": "????",
    "actors": [
      {"id": "01", "name": "leonardo di caprio"},
      {"id": "02", "name": " nicolas cage"},
      {"id": "03", "name": " natalie portman"}
    ]
  },
  {
    "id": "22",
    "name": "el padrino 2",
    "genre": "mafiosos",
    "director": "???",
    "year": "????",
    "actors": [
      {"id": "01", "name": "leonardo di caprio"},
      {"id": "02", "name": " nicolas cage"},
      {"id": "03", "name": " natalie portman"}
    ]
  },
  {
    "id": "23",
    "name": "se lo que hicistes el ultimo verano",
    "genre": "mafiosos",
    "director": "???",
    "year": "????",
    "actors": [
      {"id": "01", "name": "leonardo di caprio"},
      {"id": "02", "name": " nicolas cage"},
      {"id": "03", "name": " natalie portman"}
    ]
  }
]
